a2conn/__init__.py
a2conn/mod1.py
a2conn/mod2.py
a2conn/zebra.py
a2connect/__init__.py
a2connect/mod1.py
a2connect/mod2.py
a2connect/zebra.py
a2connect-0.1.2.dist-info/METADATA
a2connect-0.1.2.dist-info/WHEEL
a2connect-0.1.2.dist-info/entry_points.txt
a2connect-0.1.2.dist-info/top_level.txt
a2connect-0.1.2.dist-info/RECORD
